compliance_suite/__init__.py
compliance_suite/cli.py
compliance_suite/node.py
compliance_suite/report_server.py
compliance_suite/runner.py
compliance_suite/schema_validator.py
compliance_suite/user_config_parser.py
compliance_suite/config/__init__.py
compliance_suite/config/constants.py
compliance_suite/config/content_test_instances.py
compliance_suite/config/graph.py
compliance_suite/config/tests.py
compliance_suite/elements/__init__.py
compliance_suite/elements/api_case.py
compliance_suite/elements/api_component.py
compliance_suite/elements/case.py
compliance_suite/elements/component.py
compliance_suite/elements/content_case.py
compliance_suite/elements/content_component.py
compliance_suite/elements/element.py
compliance_suite/elements/executor.py
compliance_suite/exceptions/__init__.py
compliance_suite/exceptions/argument_exception.py
compliance_suite/exceptions/test_status_exception.py
compliance_suite/exceptions/user_config_exception.py
compliance_suite/functions/__init__.py
compliance_suite/functions/attribute_handlers.py
compliance_suite/functions/content_testing.py
compliance_suite/functions/download_matrix.py
compliance_suite/functions/general.py
compliance_suite/functions/parameter.py
compliance_suite/functions/schema.py
compliance_suite/functions/update_server_settings.py
compliance_suite/schemas/__init__.py
compliance_suite/schemas/rnaget-continuous.json
compliance_suite/schemas/rnaget-empty-array.json
compliance_suite/schemas/rnaget-empty.json
compliance_suite/schemas/rnaget-error.json
compliance_suite/schemas/rnaget-expression.json
compliance_suite/schemas/rnaget-project.json
compliance_suite/schemas/rnaget-reqid-template.json
compliance_suite/schemas/rnaget-reqsearchparams-array-template.json
compliance_suite/schemas/rnaget-reqsearchparams-template.json
compliance_suite/schemas/rnaget-search-filter-array.json
compliance_suite/schemas/rnaget-search-filter.json
compliance_suite/schemas/rnaget-string-array.json
compliance_suite/schemas/rnaget-study.json
ga4gh_rnaget_compliance-1.0.0.dist-info/LICENSE
ga4gh_rnaget_compliance-1.0.0.dist-info/METADATA
ga4gh_rnaget_compliance-1.0.0.dist-info/WHEEL
ga4gh_rnaget_compliance-1.0.0.dist-info/entry_points.txt
ga4gh_rnaget_compliance-1.0.0.dist-info/top_level.txt
ga4gh_rnaget_compliance-1.0.0.dist-info/RECORD
