Metadata-Version: 2.1
Name: ga4gh-rnaget-compliance
Version: 1.0.0
Summary: Reports web service compliance to GA4GH RNAget specification
Home-page: https://github.com/ga4gh-rnaseq/rnaget-compliance-suite
Author: Jeremy Adams
Author-email: jeremy.adams@ga4gh.org
License: UNKNOWN
Platform: UNKNOWN
Classifier: Programming Language :: Python :: 3.6
Classifier: Programming Language :: Python :: 3.7
Classifier: License :: OSI Approved :: Apache Software License
Classifier: Operating System :: OS Independent
Classifier: Natural Language :: English
Classifier: Topic :: Scientific/Engineering :: Bio-Informatics
Requires-Dist: requests
Requires-Dist: click
Requires-Dist: jsonschema
Requires-Dist: PyYAML
Requires-Dist: Jinja2
Requires-Dist: loompy
